thorpt/JUN92hp.txt
thorpt/THERIN
thorpt/XBIN
thorpt/__init__.py
thorpt/debugging_recorder.txt
thorpt/ds62mp.txt
thorpt/layermodel.txt
thorpt/start_ThorPT.py
thorpt/tc55.txt
thorpt/tc55_Serp.txt
thorpt/td-ds62-mb50-v07.txt
thorpt/theriak.ini
thorpt/thorpt_dash.py
thorpt/xorki.py
thorpt/.vscode/settings.json
thorpt/DataFiles/DO18db2.0.3.dat
thorpt/DataFiles/DataFormattingForTranslationDatabases.txt
thorpt/DataFiles/MINERAL_NAMES_JUN92hp_to_XMT.txt
thorpt/DataFiles/MINERAL_NAMES_ds62mp_to_XMT.txt
thorpt/DataFiles/MINERAL_NAMES_tc55_AngiRaim_to_XMT.txt
thorpt/DataFiles/MINERAL_NAMES_tc55_Serp_to_XMT.txt
thorpt/DataFiles/MINERAL_NAMES_tc55_TotoPierre_F3_to_XMT.txt
thorpt/DataFiles/MINERAL_NAMES_tc55_TotoPierre_to_XMT.txt
thorpt/DataFiles/MINERAL_NAMES_tc55_to_XMT.txt
thorpt/DataFiles/MINERAL_NAMES_td-ds62-mb50-v07_to_XMT.txt
thorpt/DataFiles/SSModel_JUN92.txt.txt
thorpt/DataFiles/SSModel_JUN92hp.txt.txt
thorpt/DataFiles/SSModel_ds62mp.txt.txt
thorpt/DataFiles/SSModel_tc55.txt.txt
thorpt/DataFiles/SSModel_tc55_AngiRaim.txt.txt
thorpt/DataFiles/SSModel_tc55_Serp.txt.txt
thorpt/DataFiles/SSModel_tc55_TotoPierre.txt.txt
thorpt/DataFiles/SSModel_tc55_TotoPierre_F3.txt.txt
thorpt/DataFiles/SSModel_tc55_italy.txt.txt
thorpt/DataFiles/SSModel_td-ds62-mb50-v07.txt.txt
thorpt/DataFiles/XMap_MinColors.txt
thorpt/DataFiles/sound/Tequila.mp3
thorpt/DataFiles/sound/wow.mp3
thorpt/valhalla/DEF_td-ds62-mb50-02.txt
thorpt/valhalla/JUN92hp.txt
thorpt/valhalla/Pathfinder.py
thorpt/valhalla/THERIN
thorpt/valhalla/XBIN
thorpt/valhalla/__init__.py
thorpt/valhalla/ds62mp.txt
thorpt/valhalla/layermodel.txt
thorpt/valhalla/routines_ThorPT.py
thorpt/valhalla/tc55.txt
thorpt/valhalla/tc55_Serp.txt
thorpt/valhalla/td-ds62-mb50-v07.txt
thorpt/valhalla/theriak.ini
thorpt/valhalla/tunorrad.py
thorpt/valhalla/DataFiles/DO18db2.0.3.dat
thorpt/valhalla/DataFiles/MINERAL_NAMES_JUN92hp_to_XMT.txt
thorpt/valhalla/DataFiles/MINERAL_NAMES_ds62mp_to_XMT.txt
thorpt-1.0.7.dist-info/METADATA
thorpt-1.0.7.dist-info/WHEEL
thorpt-1.0.7.dist-info/licenses/LICENSE
thorpt-1.0.7.dist-info/RECORD
