Metadata-Version: 2.4
Name: thorpt
Version: 1.0.7
Summary: Petrochemical modelling software ThorPT
Project-URL: Homepage, https://github.com/neoscalc/ThorPT
Project-URL: Bug Tracker, https://github.com/neoscalc/ThorPT/issues
Author-email: "Thorsten A. Markmann" <thorsten.markmann@unibe.ch>
License-File: LICENSE
Classifier: License :: OSI Approved :: GNU General Public License v3 (GPLv3)
Classifier: Operating System :: OS Independent
Classifier: Programming Language :: Python :: 3
Classifier: Topic :: Scientific/Engineering
Requires-Python: >=3.9
Requires-Dist: h5py
Requires-Dist: imageio
Requires-Dist: julia
Requires-Dist: keyboard
Requires-Dist: matplotlib
Requires-Dist: numpy
Requires-Dist: pandas
Requires-Dist: pygame
Requires-Dist: pyqt5
Requires-Dist: scipy
Requires-Dist: seaborn
Requires-Dist: tqdm
